CHANGES.rst
LICENSE
MANIFEST.in
README.rst
iresign.py
setup.py
iResign.egg-info/PKG-INFO
iResign.egg-info/SOURCES.txt
iResign.egg-info/dependency_links.txt
iResign.egg-info/top_level.txt