Metadata-Version: 1.1
Name: iResign
Version: 0.2
Summary: A tool for recodesigning iOS applications.
Home-page: https://github.com/ikalnitsky/iResign
Author: Igor Kalnitsky
Author-email: igor@kalnitsky.org
License: BSD
Platform: MacOS
Classifier: Intended Audience :: Developers
Classifier: License :: OSI Approved :: BSD License
Classifier: Operating System :: MacOS
Classifier: Programming Language :: Python
Classifier: Programming Language :: Python :: 2
Classifier: Programming Language :: Python :: 2.7
Classifier: Programming Language :: Python :: 3
Classifier: Programming Language :: Python :: 3.1
Classifier: Programming Language :: Python :: 3.2
Classifier: Programming Language :: Python :: 3.3
